h5pickle/__init__.py
h5pickle-0.4.2.dist-info/LICENSE
h5pickle-0.4.2.dist-info/METADATA
h5pickle-0.4.2.dist-info/WHEEL
h5pickle-0.4.2.dist-info/top_level.txt
h5pickle-0.4.2.dist-info/RECORD
