Metadata-Version: 2.1
Name: h5pickle
Version: 0.4.2
Summary: Wrap h5py objects to allow pickling
Home-page: https://github.com/exteris/h5pickle
Author: Daan van Vugt
Author-email: daanvanvugt@gmail.com
License: UNKNOWN
Download-URL: https://github.com/exteris/h5pickle/archive/0.4.2.tar.gz
Keywords: h5py,hdf5,pickle,dask,python
Platform: UNKNOWN
Requires-Dist: h5py
Requires-Dist: cachetools
